request_broker/__init__.py
request_broker/middleware.py
request_broker-0.0.1.dist-info/METADATA
request_broker-0.0.1.dist-info/WHEEL
request_broker-0.0.1.dist-info/top_level.txt
request_broker-0.0.1.dist-info/RECORD
