Metadata-Version: 2.4
Name: request_broker
Version: 0.0.1
Summary: A Request Broker for Django
Author-email: tojeca4420 <tojeca4420@cameltok.com>
License-Expression: MIT
Project-URL: Homepage, https://github.com/pypa/sampleproject
Project-URL: Issues, https://github.com/pypa/sampleproject/issues
Classifier: Development Status :: 5 - Production/Stable
Classifier: Framework :: Django
Classifier: Programming Language :: Python :: 3
Classifier: Operating System :: OS Independent
Requires-Python: >=3.0
